eventsourcing_kurrentdb/__init__.py
eventsourcing_kurrentdb/factory.py
eventsourcing_kurrentdb/py.typed
eventsourcing_kurrentdb/recorders.py
eventsourcing_kurrentdb-1.2.2.dist-info/LICENSE
eventsourcing_kurrentdb-1.2.2.dist-info/METADATA
eventsourcing_kurrentdb-1.2.2.dist-info/WHEEL
eventsourcing_kurrentdb-1.2.2.dist-info/RECORD
