Metadata-Version: 2.3
Name: eventsourcing-kurrentdb
Version: 1.2.2
Summary: Python package for eventsourcing with KurrentDB
License: BSD-3-Clause
Author: John Bywater
Author-email: john.bywater@appropriatesoftware.net
Requires-Python: >=3.9.2
Classifier: Development Status :: 5 - Production/Stable
Classifier: Intended Audience :: Developers
Classifier: License :: OSI Approved :: BSD License
Classifier: Programming Language :: Python :: 3
Classifier: Programming Language :: Python :: 3.10
Classifier: Programming Language :: Python :: 3.11
Classifier: Programming Language :: Python :: 3.12
Classifier: Programming Language :: Python :: 3.13
Classifier: Programming Language :: Python :: 3.9
Classifier: Programming Language :: Python
Classifier: Topic :: Software Development :: Libraries :: Python Modules
Requires-Dist: eventsourcing (>=9.4.5,<10.0)
Requires-Dist: kurrentdbclient (>=1.0.2,<2.0)
Project-URL: Homepage, https://github.com/pyeventsourcing/eventsourcing-kurrentdb
Project-URL: Repository, https://github.com/pyeventsourcing/eventsourcing-kurrentdb
